pydregiondata/__init__.py
pydregiondata/_parse_data.py
pydregiondata/dregiondata.py
pydregiondata/_ext/_data/00000.nc
pydregiondata/_ext/_data/00001.nc
pydregiondata/_ext/_data/000010.nc
pydregiondata/_ext/_data/000011.nc
pydregiondata/_ext/_data/000012.nc
pydregiondata/_ext/_data/000013.nc
pydregiondata/_ext/_data/000014.nc
pydregiondata/_ext/_data/000015.nc
pydregiondata/_ext/_data/000016.nc
pydregiondata/_ext/_data/000017.nc
pydregiondata/_ext/_data/000018.nc
pydregiondata/_ext/_data/000019.nc
pydregiondata/_ext/_data/00002.nc
pydregiondata/_ext/_data/000020.nc
pydregiondata/_ext/_data/000021.nc
pydregiondata/_ext/_data/000022.nc
pydregiondata/_ext/_data/00003.nc
pydregiondata/_ext/_data/00004.nc
pydregiondata/_ext/_data/00005.nc
pydregiondata/_ext/_data/00006.nc
pydregiondata/_ext/_data/00007.nc
pydregiondata/_ext/_data/00008.nc
pydregiondata/_ext/_data/00009.nc
pydregiondata-0.0.1a9.dist-info/METADATA
pydregiondata-0.0.1a9.dist-info/WHEEL
pydregiondata-0.0.1a9.dist-info/top_level.txt
pydregiondata-0.0.1a9.dist-info/RECORD
